Metadata-Version: 2.1
Name: diterator
Version: 0.9
Summary: Iterator and wrapper for processing IATI activities.
Home-page: UNKNOWN
Author: David Megginson
Author-email: megginson@un.org
License: UNKNOWN
Platform: UNKNOWN
